xtable_py/__init__.py
xtable_py/airflow_plugin.py
xtable_py/xtable_cmd.py
xtable_py-0.0.24.dist-info/entry_points.txt
xtable_py-0.0.24.dist-info/LICENSE
xtable_py-0.0.24.dist-info/WHEEL
xtable_py-0.0.24.dist-info/METADATA
xtable_py-0.0.24.dist-info/RECORD
